pimondrian/10000pi.txt
pimondrian/__init__.py
pimondrian/__main__.py
pimondrian/colors.txt
pimondrian/pimondrian.py
pimondrian-1.2.0.dist-info/LICENSE
pimondrian-1.2.0.dist-info/METADATA
pimondrian-1.2.0.dist-info/WHEEL
pimondrian-1.2.0.dist-info/entry_points.txt
pimondrian-1.2.0.dist-info/top_level.txt
pimondrian-1.2.0.dist-info/RECORD
