Metadata-Version: 2.1
Name: pimondrian
Version: 1.2.0
Summary: Draw Paintings as Mondrian
Home-page: https://github.com/psicobyte/pimondrian_module
Author: Allan Psicobyte
Author-email: psicobyte@gmail.com
License: UNKNOWN
Keywords: mondrian,art,painting
Platform: UNKNOWN
Classifier: Programming Language :: Python :: 3
Classifier: License :: OSI Approved :: GNU Affero General Public License v3 or later (AGPLv3+)
Classifier: Operating System :: OS Independent
Classifier: Topic :: Artistic Software
Requires-Python: >=3.6
Requires-Dist: pillow
